tracemorph/__init__.py
tracemorph/core/__init__.py
tracemorph/core/builder.py
tracemorph/core/error_hook.py
tracemorph/core/tracer.py
tracemorph/output/__init__.py
tracemorph/output/human_writer.py
tracemorph/output/json_exporter.py
tracemorph/store/__init__.py
tracemorph/store/trace_log.py
tracemorph-0.1.5.dist-info/licenses/LICENSE
venv/Lib/site-packages/typing_extensions.py
venv/Lib/site-packages/_distutils_hack/__init__.py
venv/Lib/site-packages/_distutils_hack/override.py
venv/Lib/site-packages/backports/__init__.py
venv/Lib/site-packages/backports/tarfile/__init__.py
venv/Lib/site-packages/backports/tarfile/__main__.py
venv/Lib/site-packages/backports/tarfile/compat/__init__.py
venv/Lib/site-packages/backports/tarfile/compat/py38.py
venv/Lib/site-packages/build/__init__.py
venv/Lib/site-packages/build/__main__.py
venv/Lib/site-packages/build/_builder.py
venv/Lib/site-packages/build/_ctx.py
venv/Lib/site-packages/build/_exceptions.py
venv/Lib/site-packages/build/_types.py
venv/Lib/site-packages/build/_util.py
venv/Lib/site-packages/build/env.py
venv/Lib/site-packages/build/py.typed
venv/Lib/site-packages/build/util.py
venv/Lib/site-packages/build/_compat/__init__.py
venv/Lib/site-packages/build/_compat/importlib.py
venv/Lib/site-packages/build/_compat/tarfile.py
venv/Lib/site-packages/build/_compat/tomllib.py
venv/Lib/site-packages/certifi/__init__.py
venv/Lib/site-packages/certifi/__main__.py
venv/Lib/site-packages/certifi/core.py
venv/Lib/site-packages/certifi/py.typed
venv/Lib/site-packages/charset_normalizer/__init__.py
venv/Lib/site-packages/charset_normalizer/__main__.py
venv/Lib/site-packages/charset_normalizer/api.py
venv/Lib/site-packages/charset_normalizer/cd.py
venv/Lib/site-packages/charset_normalizer/constant.py
venv/Lib/site-packages/charset_normalizer/legacy.py
venv/Lib/site-packages/charset_normalizer/md.py
venv/Lib/site-packages/charset_normalizer/models.py
venv/Lib/site-packages/charset_normalizer/py.typed
venv/Lib/site-packages/charset_normalizer/utils.py
tracemorph-0.1.5.dist-info/METADATA
tracemorph-0.1.5.dist-info/WHEEL
tracemorph-0.1.5.dist-info/top_level.txt
tracemorph-0.1.5.dist-info/RECORD
