Metadata-Version: 2.4
Name: tracemorph
Version: 0.1.5
Summary: Function execution tracing, visualization, and narrative builder for Python apps.
Home-page: https://github.com/lahadiyani/tracemorph
Author: Hadi
Author-email: Hadi <lahadiyani@gmail.com>
License: Custom NonCommercial License
Project-URL: Homepage, https://github.com/lahadiyani/tracemorph
Project-URL: Source, https://github.com/lahadiyani/tracemorph
Project-URL: Tracker, https://github.com/lahadiyani/tracemorph/issues
Keywords: tracing,execution,debug,visualization,narrative,python
Classifier: Programming Language :: Python :: 3
Classifier: Operating System :: OS Independent
Classifier: License :: Other/Proprietary License
Classifier: Intended Audience :: Developers
Classifier: Topic :: Software Development :: Debuggers
Requires-Python: >=3.7
License-File: LICENSE
Requires-Dist: requests
Requires-Dist: flask
Requires-Dist: colorama
Dynamic: author
Dynamic: home-page
Dynamic: license-file
Dynamic: requires-python
